jqtrade/__init__.py
jqtrade/__main__.py
jqtrade/account/__init__.py
jqtrade/account/account.py
jqtrade/account/api.py
jqtrade/account/config.py
jqtrade/account/order.py
jqtrade/account/portfolio.py
jqtrade/account/position.py
jqtrade/account/trade_gate.py
jqtrade/common/__init__.py
jqtrade/common/exceptions.py
jqtrade/common/log.py
jqtrade/common/utils.py
jqtrade/scheduler/__init__.py
jqtrade/scheduler/api.py
jqtrade/scheduler/bus.py
jqtrade/scheduler/config.py
jqtrade/scheduler/context.py
jqtrade/scheduler/event.py
jqtrade/scheduler/event_source.py
jqtrade/scheduler/loader.py
jqtrade/scheduler/loop.py
jqtrade/scheduler/message.py
jqtrade/scheduler/queue.py
jqtrade/scheduler/runner.py
jqtrade/scheduler/strategy.py
jqtrade/scheduler/utils.py
jqtrade-1.0.2.dist-info/LICENSE
jqtrade-1.0.2.dist-info/METADATA
jqtrade-1.0.2.dist-info/WHEEL
jqtrade-1.0.2.dist-info/entry_points.txt
jqtrade-1.0.2.dist-info/top_level.txt
jqtrade-1.0.2.dist-info/RECORD
