Metadata-Version: 2.1
Name: jqtrade
Version: 1.0.2
Summary: Simple trading framework for Quant
Home-page: https://github.com/ZiaWang/jqtrade
Author: ('wangzihao',)
Author-email: wow_zihao@163.com
Maintainer: ('wangzihao',)
Maintainer-email: wow_zihao@163.com
License: MIT License
Platform: all
Classifier: Programming Language :: Python :: 3
Classifier: Operating System :: Microsoft :: Windows
Classifier: Operating System :: Unix
Classifier: License :: OSI Approved :: MIT License
Requires-Python: >=3.6.2, <=3.9.18
License-File: LICENSE
Requires-Dist: pyuv (>=1.4.0)
Requires-Dist: psutil (>=5.9.6)
Requires-Dist: pandas (>=1.1.5)
Requires-Dist: portalocker (>=2.7.0)
